{
  "VTBS": "✈️ VTBS ATIS MONITOR\nUpdate: 2026-04-18 05:38:12\n==============================\n\nVTBS ARR ATIS T\n1730Z VTBS ARR ATIS T\n1731Z EXP ILS Z APCH ARR RWY 19 OR RNP APCH RWY 20R\n,RETIL RWY 19 U/S\n,PILOT SHALL ADZ BKK APCH ON INITIAL CTC IF UNA TO CONDUCT RNP APCH DUE TO\nOPERATIONAL CONSTRAINT\n1730Z WIND 170/9KT VIS 10KM CLD SCT 2000FT T30 DP25 QNH 1009HPA TREND NOSIG\nADZ BKK APCH ON INITIAL CONTACT THAT YOU HAVE INFO T\n--------------------\nVTBS DEP ATIS N\n1830Z VTBS DEP ATIS N\n1831Z DEP RWY 20L\n,\n,AFT AIRBORNE ALL DEPARTING ACFT SHALL CTC\n119.25\n1830Z WIND 190/10KT VIS 10KM CLD FEW 2000FT\nT30 DP25 QNH 1008HPA TREND NOSIG\nADZ GND ON INITIAL CONTACT THAT YOU HAVE INFO\nN\n--------------------\n",
  "ZHHH": "✈️ ZHHH ATIS MONITOR\nUpdate: 2026-04-18 05:38:11\n==============================\n\nZHHH ARR ATIS F\n1900Z EXP ILSDME APCH\nLDG RWY 04\nTA 3000\nWIND 000/0MPS\nVIS 6000M\nNSC\nT 19 /DP 19\nQNH 1012 HPA\nSINGLE RUNWAY OPERATION\nRNAV ARR IS AVAIL\nADZ YOU HAVE INFO F.\n--------------------\nZHHH DEP ATIS E\n1600Z DEP RWY 04\nTA 3000\nWIND 220/2MPS\nVIS 5000M\nBR\nNSC\nT 18 /DP 18\nQNH 1014 HPA\nSINGLE RUNWAY OPERATION\nRNAV DEP IS AVAIL\nADZ YOU HAVE INFO E.\n--------------------\n",
  "ZSOF": "✈️ ZSOF ATIS MONITOR\nUpdate: 2026-04-18 04:50:29\n==============================\n\nZSOF ARR ATIS T\n1400Z EXP ILS Z APCH\nLDG RWY 33\nWIND 090 DEG 3 MPS\nVIS 6000\nNSC\nT 20 /DP 16\nQNH 1014 HPA\nTRL 3600\nVISUAL APPROACH\nAVAILABLE AT XINQIAO\nAIRPORT\nADZ YOU HAVE INFO T.\n--------------------\nZSOF DEP ATIS G\n0200Z DEP RWY 33\nWIND 290 DEG 2 MPS 220V350 DEG\nVIS 3000\nBR\nCLD SCT 480M\nT 21 /DP 18\nQNH 1016 HPA\nTRL 3600\nADZ YOU HAVE INFO G.\n--------------------\n",
  "WMKK": "✈️ WMKK ATIS MONITOR\nUpdate: 2026-04-18 05:38:15\n==============================\n\nWMKK ARR ATIS F\n2104Z WMKK ARR INFO F.\nTIME 2100.\nINDEPENDENT PARALLEL APPROACHES FOR RWY 32 R AND 33 ARE IN PROGRESS.\nEXP RNAV / ILS APCH FOR RWY 32 RIGHT.\nEXP RNAV / ILS APCH FOR RWY 33.\nWIND RWY 32R 040 DEG, 2 KT. WIND RWY 32L 030 DEG, 3 KT.\nWIND RWY 33 330 DEG, 2 KT.\nVIS RWY 32R TDZ NOT AVBL.\nVIS RWY 33 TDZ NOT AVBL.\nCLD FEW CB 1700 FT.\nT 26.\nDP 24.\nQNH 1007.\nNOSIG.\nAT FIRST CONTACT WITH LUMPUR RADAR, NOTIFY RCPT OF F\n--------------------\nWMKK DEP ATIS O\n2033Z WMKK DEP INFO O.\nTIME 2030.\nINDEPENDENT PARALLEL DEPARTURES FOR RWY 32 R AND 33 ARE IN PROGRESS.\nRWY 32 RIGHT.\nRWY 33.\nWIND RWY 32R 070 DEG, 2 KT, VRB BTN 010. WIND RWY 32L 080 DEG, 1 KT, VRB BTN 010 AND 150 DEG.\nWIND RWY 33 CALM.\nVIS RWY 32R TDZ NOT AVBL.\nVIS RWY 33 TDZ NOT AVBL.\nCLD FEW CB 1700 FT.\nT 26.\nDP 24.\nQNH 1007.\nNOSIG.\nALL DEP ACFT TO CONTACT LUMPUR DEP AT 135 DECIMAL 25 MHZ WHEN ABN.\nAT FIRST CONTACT WITH LUMPUR GROUND, NOTIFY RCPT OF O\n--------------------\n",
  "ZGNN": "✈️ ZGNN ATIS MONITOR\nUpdate: 2026-04-18 04:49:48\n==============================\n\nZGNN ARR ATIS G\n0713Z EXP ILS-W APCH\nLDG RWY 05\nSFC COND & BA NOTICE:RWYCC 05 6/6/6\nISSUED AT 0606Z ALL PARTS NR NR NR\nTRL 3600\nWIND RWY 05 TDZ 080/2MPS MID 060/3MPS\nEND 090/2MPS\nVIS RWY 05 TDZ 9999M MID 9999M END 9999M\nRVR RWY 05 TDZ P2000M MID P2000M END\nP2000M\nCLD SCT 330M /OVC 1200M\nT 24 /DP 22\nQNH 1011 HPA QFE RWY 05 TDZ 995 HPA END\n996 HPA\nMILITARY ACTIVITY\nIN CASE OF MISSED APCH,CLIMB TO 1200\nMETERS ON QFE\nADZ YOU HAVE INFO G.\n--------------------\nZGNN DEP ATIS C\n1200Z DEP RWY 05\nTRL 3600\nWIND RWY 05 TDZ 120/4MPS MID 110/4MPS\nEND 120/4MPS\nCAVOK\nT 29 /DP 24\nQNH 1005 HPA QFE RWY 05 TDZ 990 HPA END\n990 HPA\nINTERSECTION TAKE OFF VIA B3\nADZ YOU HAVE INFO C.\n--------------------\n",
  "VVNB": "✈️ VVNB ATIS MONITOR\nUpdate: 2026-04-18 05:38:14\n==============================\n\nVVNB ARR ATIS P\n2130Z VVNB INFO P 2130Z. ILS X RWY 11L. DPTG\nRWY 11R AND ARR RWY 11L .. 2130Z. WIND RWY\n11R TDZ 070/5KT MID 080/4KT END 090/4KT RWY\n11L TDZ 080/5KT END 090/4KT VIS 8KM CLD BKN\n2500FT BKN 3000FT BKN 4400FT T24 DP23 QNH\n1010HPA TREND NOSIG. ADZ ON INITIAL CTC YOU\nHAVE INFO P.\n--------------------\nVVNB DEP ATIS P\n2130Z VVNB INFO P\n2130Z. ILS X RWY 11L.\nDPTG RWY 11R AND ARR\nRWY 11L .. 2130Z. WIND\nRWY 11R TDZ 070/5KT MID\n080/4KT END 090/4KT RWY\n11L TDZ 080/5KT END\n090/4KT VIS 8KM CLD BKN\n2500FT BKN 3000FT BKN\n4400FT T24 DP23 QNH\n1010HPA TREND NOSIG.\nADZ ON INITIAL CTC YOU\nHAVE INFO P.\n--------------------\n",
  "ZUGY": "✈️ ZUGY ATIS MONITOR\nUpdate: 2026-04-18 05:39:36\n==============================\n\nZUGY ARR ATIS M\n0800Z EXP RNAV ILS APCH\nLDG RWY 01R\nTA 3000 /TRL 3600\nWIND 360/2MPS VRB BTN 310/ AND 040/\nVIS 9999M\nCLD SCT 990M\nT 21 /DP 14\nQNH 1016 HPA\nTHERE IS LIGHT TO MODERATE TURBULENCE\nABOVE 4000 METERS ON QNH\nADZ YOU HAVE INFO M.\n--------------------\nZUGY DEP ATIS B\n1200Z DEP RWY 19L\nTA 3000 /TRL 3600\nWIND 100/2MPS VRB BTN 070/ AND 150/\nVIS 9999M\nCLD FEW 1380M\nT 14 /DP 12\nQNH 1014 HPA\nTHERE IS LIGHT TO MODERATE TURBULENCE\nABOVE 2500 METERS ON QNH\nADZ YOU HAVE INFO B.\n--------------------\n",
  "ZUUU": "✈️ ZUUU ATIS MONITOR\nUpdate: 2026-04-18 05:39:26\n==============================\n\nZUUU ARR ATIS F\n1830Z EXP RNAV ILS APCH\nLDG RWY 02L\nTA 3000 /TRL 3600\nWIND RWY 02L TDZ 230/1MPS MID 000/0MPS\nEND 000/0MPS\nCAVOK\nT 18 /DP 14\nQNH 1012 HPA\nADZ YOU HAVE INFO F.\n--------------------\nZUUU DEP ATIS J\n2000Z DEP RWY 02L\nTA 3000 /TRL 3600\nWIND RWY 02L TDZ 200/1MPS MID 210/1MPS\nEND 000/0MPS\nCAVOK\nT 16 /DP 14\nQNH 1011 HPA\nRWY STATUS 02L  DEP FREQ 126.35 DLV FREQ\n123.0\nADZ YOU HAVE INFO J.\n--------------------\n",
  "RKSI": "✈️ RKSI ATIS MONITOR\nUpdate: 2026-04-18 05:38:14\n==============================\n\nRKSI ARR ATIS S\n2100Z\nEXP SIMUL PARALLEL ILS APCH RWY 33R AND ILS APCH RWY 34L\nEXP LDG RWY INFO FROM SEOUL APP\nWIND 360/3KT\nVIS 6KM\nCLD NSC\nT 9\nDP 9\nQNH 1016\nCAUTION BIRD ACTIVITY\nEXP REBIT 1Y OLMEN 1Y GUKDO 2E KARBU 2E ARRIVAL\nVACATE RWY33R VIA TWY ECHO NOT AVAILABLE UNLESS AUTHORIZED BY ATC PRIOR TO LANDING\nGPS SIGNAL UNRELIABLE DUE TO GPS INTERFERENCE IN SEOUL APCH AREA\n--------------------\nRKSI DEP ATIS C\n1730Z\nDEP RWY 34R\nWIND VRB BTN 170/ AND 250/1KT\nCAVOK\nT 10\nDP 9\nQNH 1016\nRWY 33L UNUSABLE DUE TO WORK IN PROGRESS\nRWY 33R UNUSABLE DUE TO WORK IN PROGRESS\nCAUTION BIRD ACTIVITY\nRWY 34R EXPECT SID BOPTA2Y NOPIK2Y EGOBA2Y OSPOT2Y\nDEP FREQ 125.15\nGPS SIGNAL UNRELIABLE DUE TO GPS INTERFERENCE IN SEOUL APCH AREA\n--------------------\n",
  "ZGKL": "✈️ ZGKL ATIS MONITOR\nUpdate: 2026-04-18 05:38:13\n==============================\n\nZGKL ARR ATIS O\n1700Z EXP ILSDME APCH\nLDG RWY 01\nTA 3000\nWIND 000 DEG 0 MPS\nCAVOK\nT 18 /DP 17\nQNH 1015 HPA\nADZ YOU HAVE INFO O.\n--------------------\nZGKL DEP ATIS Q\n1305Z DEP RWY 01\nTA 3000\nWIND 040 DEG 2 MPS\nVIS 8000\nCLD SCT 690M /BKN 1380M\nT 20 /DP 19\nQNH 1009 HPA\nADZ YOU HAVE INFO Q.\n--------------------\n",
  "VHHH": "✈️ VHHH ATIS MONITOR\nUpdate: 2026-04-18 05:38:14\n==============================\n\nVHHH ARR ATIS B\n2104Z\nARRIVALS, RWY 07L.\nEXP ILS  APCH, RWY 07L.\nRWY 07 RUNWAY CONDITION REPORT AT 1656Z.\nRWY 07L RUNWAY CONDITION CODES 5 , 5 , 5 .\nRWY SFC ALL PARTS   WET.\nRWY 07C/R CLSD. WIND 340/05KT VIS 6KM CLD FEW\n800FT T23 DP20 QNH 1011HPA=\nACKNOWLEDGE INFO B ON FIRST CTC WITH APP.\n--------------------\nVHHH DEP ATIS X\n2006Z\nDEPARTURES, RWY 07L.\nRWY 07 RUNWAY CONDITION REPORT AT 1656Z.\nRWY 07L RUNWAY CONDITION CODES 5 , 5 , 5 .\nRWY SFC ALL PARTS   WET.\nRWY 07C/R CLSD.\nWIND VRB05KT VIS 7KM CLD FEW 800FT T23 DP20\nQNH 1010HPA=\nACKNOWLEDGE INFO X ON FIRST CTC WITH DELIVERY\n.\n--------------------\n",
  "VTBD": "✈️ VTBD ATIS MONITOR\nUpdate: 2026-04-18 05:38:13\n==============================\n\nVTBD ARR ATIS L\n0700Z VTBD ARR ATIS L\n0701Z EXP ILS Z APCH RWY 21, RWY IN USE 21\n0700Z WIND 200/10KT VRB BTN 160/ AND\n230/ VIS 10KM CLD FEW 2000FT SCT 4000FT T37\nDP25 QNH 1007HPA TREND NOSIG\nADZ CONTROLLER WHEN INITIAL CONTACT YOU HAVE\nINFO L\n--------------------\nVTBD DEP ATIS S\n0130Z RWY IN\nUSE 21 0130Z WIND 260/9KT VRB\nBTN 230/ AND 290/ VIS 10KM CLD\nFEW 3000FT T32 DP19 QNH\n1010HPA TREND NOSIG ADZ\nCONTROLLER WHEN INITIAL\nCONTACT YOU HAVE INFO S\n--------------------\n",
  "VVDN": "✈️ VVDN ATIS MONITOR\nUpdate: 2026-04-18 05:39:24\n==============================\n\nVVDN ARR ATIS H\n1532Z VVDN INFO H 1532Z. ILS VICTOR\nAPPROACH 35L.. DPTG RWY 35R.. 1532Z.\nWIND 140/08KT VIS 10KM CLD OVC 800FT\nT27 DP25 QNH 1012HPA TREND NOSIG. DUE\nWORK IN PROGRESS ADVISE ECHO2 FOR\nDEPARTURE RUNWAY 35R. ADZ ON INITIAL\nCTC YOU HAVE INFO. H.\n--------------------\nVVDN DEP ATIS I\n1533Z VVDN INFO I 1533Z. ILS VICTOR\nAPPROACH 35L.. DPTG RWY 35R.. 1533Z.\nWIND 110/02KT CAVOK T27 DP24 QNH\n1008HPA TREND NOSIG. DUE WORK IN\nPROGRESS ADVISE ECHO2 FOR DEPARTURE\nRUNWAY 35R. ADZ ON INITIAL CTC YOU HAVE\nINFO. I.\n--------------------\n",
  "ZBTJ": "✈️ ZBTJ ATIS MONITOR\nUpdate: 2026-04-18 05:38:16\n==============================\n\nZBTJ ARR ATIS I\n1200Z EXP ILSDME APCH\nLDG RWY 16L\nTA 3000\nWIND 150 DEG 3 MPS\nVIS 4500\nBR\nNSC\nT 17 /DP 13\nQNH 1011 HPA\nSINGLE RUNWAY OPERATION\nMISSED APPROACH ALTITUDE 600 METERS\nREQUEST PDC ON GROUND 121.95\nADZ YOU HAVE INFO I.\n--------------------\nZBTJ DEP ATIS G\n1130Z DEP RWY 16R\nTA 3000\nWIND 150 DEG 4 MPS\nVIS 5000\nHZ\nNSC\nT 18 /DP 13\nQNH 1011 HPA\nSEGREGATED OPERATION\nMISSED APPROACH ALTITUDE 600\nMETERS\nREQUEST PDC ON GROUND 121.95\nADZ YOU HAVE INFO G.\n--------------------\n",
  "ZBAA": "✈️ ZBAA ATIS MONITOR\nUpdate: 2026-04-18 05:38:55\n==============================\n\nZBAA ARR ATIS P\n2109Z EXP ILS APCH\nDEPENDENT PARL INSTR APCH\nLDG RWY 18R & 19\nWIND VRB DEG 1 MPS\nVIS 3400\nBR\nCLD SCT 990M\nT 15 /DP 14\nQNH 1011 HPA\n18L ILS UNSERVISABLE DUE TO INSPECTION\nFLIGHT\nADZ YOU HAVE INFO P.\n--------------------\nZBAA DEP ATIS E\n1730Z DEP RWY 36L & 01\nRWY 36R IS CLSD\nWIND VRB DEG 1 MPS\nVIS 6000\nNSC\nT 16 /DP 14\nQNH 1012 HPA\nRWY INDEPENDENT PARALLEL DEP\nADZ YOU HAVE INFO E.\n--------------------\n",
  "ZSHC": "✈️ ZSHC ATIS MONITOR\nUpdate: 2026-04-18 05:38:12\n==============================\n\nZSHC ARR ATIS E\n1700Z EXP ILS OR VIS APCH\nLDG RWY 07\nWIND RWY 07 TDZ 060/3MPS MID 060/3MPS END\n090/3MPS\nVIS RWY 07 TDZ 3400M MID 3600M END 3700M\nBR\nCLD SCT 990M\nT 18 /DP 16\nQNH 1014 HPA\nEXPECT MISSED APPROACH ALTITUDE SETTING\n1200METERS\nADZ YOU HAVE INFO E.\n--------------------\nZSHC DEP ATIS L\n2030Z DEP RWY 07\nWIND RWY 07 TDZ 080/2MPS MID 090/1MPS END\n100/1MPS\nVIS RWY 07 TDZ 5000M MID 5000M END 5000M\nFBL RA BR\nCLD FEW 510M /BKN 780M\nT 17 /DP 15\nQNH 1013 HPA\nDELIVERY FREQ 118.3\nEXPECT MISSED APPROACH ALTITUDE SETTING\n1200METERS\nADZ YOU HAVE INFO L.\n--------------------\n",
  "RCKH": "✈️ RCKH ATIS MONITOR\nUpdate: 2026-04-18 05:38:13\n==============================\n\nRCKH ARR ATIS V\n2100Z\nEXPECT ILS  APPROACH\nRWY 09  ARR/DEP\nTAXIWAY ECHO,  TAXIWAY\nSIERRA THREE,  TAXIWAY\nALPHA BETWEEN RUNWAY AND\nPARKING BAY HOTEL 1\nCLOSED, DUE TO\nCONSTRUCTION WORK.\nWIND 030/04KT\nVIS  6000M\nCLD\nFEW  1000FT\nSCT  3000FT\nBKN  7000FT\nT 25 DP 21 QNH 1010HPA\nTEMPO 5000 HZ\nCAUTION BIRD ACTIVITY IN\nVINCINITY OF AERODROME.\nINFORM KAO-HSIUN APCH OR\nKAO-HSIUN TOWER ON\nINITIAL CONTACT\nYOU HAVE INFORMATION V\n--------------------\nRCKH DEP ATIS X\n0700Z\nEXPECT ILS  APPROACH\nRWY 27  ARR/DEP\nTAXIWAY ECHO,  TAXIWAY SIERRA THREE,\nTAXIWAY ALPHA BETWEEN RUNWAY AND PARKING\nBAY HOTEL 1 CLOSED, DUE TO CONSTRUCTION\nWORK.\nWIND 270/\n--------------------\n",
  "ZUCK": "✈️ ZUCK ATIS MONITOR\nUpdate: 2026-04-18 05:38:52\n==============================\n\nZUCK ARR ATIS L\n2100Z EXP ILSDME APCH\nLDG RWY 03R\nTA 3000 /TRL 3600\nWIND 360/3MPS\nCAVOK\nT 19 /DP 13\nQNH 1011 HPA\nRNAV IS AVAIL\nADZ YOU HAVE INFO L.\n--------------------\nZUCK DEP ATIS X\n0900Z DEP RWY 03L\nTA 3000 /TRL 3600\nWIND 220/2MPS VRB BTN 180/ AND 270/\nCAVOK\nT 27 /DP 13\nQNH 1011 HPA\nRNAV IS AVAIL\nADZ YOU HAVE INFO X.\n--------------------\n",
  "WSSS": "✈️ WSSS ATIS MONITOR\nUpdate: 2026-04-18 05:38:14\n==============================\n\nWSSS ARR ATIS E\n2130Z\nMETREPORT 2130Z\nILS APCHRWY 02L\nFOLLOW THE GREENS TRIAL IN PROGRESS. WHEN\nVACATING THE RWY, PILOTS TO ADHERE TO ATC\nVERBAL INSTRUCTIONS. WHEN ON TWY, PILOT TO\nADHERE TO FOLLOW THE GREENS INSTRUCTIONS.\nWHEN APPROACHING [A] JUNCTION, KEEP [A]\nLOOKOUT FOR CONTINUOUS GREENS. [IF] [A]\nBREAK IN THE GREENS IS OBSERVED, STOP AND\nCLARIFY WITH ATC.\nWIND 340/ 02KT\nVIS 10KM\nCLD FEW 1600FT\nT26 DP25\nQNH 1008HPA\nNOSIG\nACK ATIS E\n--------------------\nWSSS DEP ATIS O\n2000Z\nMETREPORT 2000Z RWY 02C\nFOLLOW THE GREENS\nTRIAL IN PROGRESS.\nWHEN VACATING THE RWY,\nPILOTS TO ADHERE TO\nATC VERBAL\nINSTRUCTIONS. WHEN ON\nTWY, PILOT TO ADHERE\nTO FOLLOW THE GREENS\nINSTRUCTIONS. WHEN\nAPPROACHING [A]\nJUNCTION, KEEP [A]\nLOOKOUT FOR CONTINUOUS\nGREENS. [IF] [A] BREAK\nIN THE GREENS IS\nOBSERVED, STOP AND\nCLARIFY WITH ATC.\nWIND 360/ 05KT\nVIS 10KM\nCLD FEW 1400FT\nT27 DP26\nQNH 1008HPA\nNOSIG\nDEP,INITIAL CMB 3000FT\nACK ATIS O\n--------------------\n",
  "RJBB": "✈️ RJBB ATIS MONITOR\nUpdate: 2026-04-18 05:38:14\n==============================\n\nRJBB ARR ATIS F\n2137Z M2130\n(APCH)ILS Z RWY06R\nLDG RWY 06R\nDEP RWY 06L\nDEP FREQ 120.85.\nM\n172130Z 07006KT 35KM FEW020CU BKN070AC\nBKN130AC 15/10 Q1017/A3005=\nQ/THREE ZERO ZERO FIVE\nSTP\n--------------------\nRJBB DEP ATIS O\n1355Z M1330\n(APCH)ILS Z RWY06R\nLDG RWY 06R\nDEP RWY 06L\nDEP FREQ 120.85.\nM\n171330Z 13010KT 25KM FEW025CU SCT180AC\nBKN/// 18/04 Q1018/A3009=\nQ/THREE ZERO ZERO NINE\nSTP\n--------------------\n",
  "ZSAM": "✈️ ZSAM ATIS MONITOR\nUpdate: 2026-04-18 05:38:31\n==============================\n\nZSAM ARR ATIS X\n1100Z EXP ILSDME APCH\nLDG RWY 05\nTA 3000\nWIND RWY 05 TDZ 140/2MPS\nEND 130/3MPS\nVIS RWY 05 TDZ 5000M MID\n7000M END 7000M\nBR\nCLD FEW TCU 690M\nT 24 /DP 22\nQNH 1010 HPA\nIN CASE\nMISSED-APPROACH,EXPECT\nCONTINUE RUNWAY\nHEADING,INITIAL ALTITUDE\n900 METERS ON QNH.IF\nRADIO FAILURE FOLLOW\nMISSED-APPROACH AS\nPUBLISHED.\nADZ YOU HAVE INFO X.\n--------------------\nZSAM DEP ATIS S\n0600Z DEP RWY 05\nTA 3000\nWIND RWY 05 TDZ 090/3MPS\nEND 090/4MPS\nVIS RWY 05 TDZ 7000M MID\n8000M END 6000M\nBR\nCLD BKN 990M\nT 27 /DP 22\nQNH 1010 HPA\nIN CASE\nMISSED-APPROACH,EXPECT\nCONTINUE RUNWAY\nHEADING,INITIAL ALTITUDE\n900 METERS ON QNH.IF\nRADIO FAILURE FOLLOW\nMISSED-APPROACH AS\nPUBLISHED.\nADZ YOU HAVE INFO S.\n--------------------\n",
  "ZSQD": "✈️ ZSQD ATIS MONITOR\nUpdate: 2026-04-18 05:38:12\n==============================\n\nZSQD ARR ATIS J\n2000Z EXP ILSDME APCH\nLDG RWY 17\nTA 3000 /TRL 3600\nWIND 160/4MPS\nVIS 4200M\nBR\nCLD BKN 120M\nT 12 /DP 12\nQNH 1015 HPA\nVISUAL APPROACH OPERATION IN\nPROGRESS.\nWHEN READY CONTACT QINGDAO\nTOWER ON 118.275\nRUNWAY 17,IF MISSED\nAPPROACH,EXPECT FOLLOW THE\nSTANDARD MISSED APPROACH\nPROCEDURE,CLIMB TO 900M ON QNH\nOR BY ATC\nADZ YOU HAVE INFO J.\n--------------------\nZSQD DEP ATIS L\n0000Z DEP RWY 16\nTA 3000 /TRL 3600\nWIND 170/4MPS\nVIS 5000M\nBR\nCLD SCT 270M /OVC 600M\nT 15 /DP 13\nQNH 1014 HPA\nSEGREGATED OPERATION\nVISUAL APPROACH OPERATION IN\nPROGRESS.\nRUNWAY 17,IF MISSED\nAPPROACH,EXPECT FOLLOW THE\nSTANDARD MISSED APPROACH\nPROCEDURE,CLIMB TO 900M ON QNH\nOR BY ATC\nRWY 17 RWYCC 5/5/5 ISSUED AT\n1940UTC WET/WET/WET DPT\nNR/NR/NR COV\n100PCT/100PCT/100PCT\nADZ YOU HAVE INFO L.\n--------------------\n",
  "RKPC": "✈️ RKPC ATIS MONITOR\nUpdate: 2026-04-18 05:38:11\n==============================\n\nRKPC ARR ATIS C\n2100Z\nEXP ILS Z RWY 07 APP\nDEP RWY 07\nDEP FREQ WILL BE 121.200\nWND 260 AT 1 KTS\nVARIABLE BTWN 210 DEGREES AND 300 DEGREES 01 KTS\nVIS 1 THOUSAND M\nWITH MIST\nRVR RWY 07 TOUCHDOWN 1 THOUSAND 4 HUNDRED M\nMID 1 THOUSAND 2 HUNDRED M\nSTOP 1 THOUSAND 4 HUNDRED M\nCLD\nBROKEN 2 HUNDRED FT\nTP 15 DEGREES CELSIUS\nDP 15\nQNH 1012 HPA 2988 INCHES\nAFTER LANDING CONTACT JEJU GND WHEN TURNING ONTO THE RAPID EXIT TAXIWAY TO VACATE RWY\nDO NOT STOP ON THE RAPID EXIT TAXIWAY\nADZ YOU HAVE INFO C\n--------------------\nRKPC DEP ATIS O\n0800Z\nEXP ILS Z RWY 07 APP\nDEP RWY 07\nDEP FREQ WILL BE 121.200\nWND 080 AT 18 KTS\nVARIABLE BTWN 030 DEGREES AND 100 DEGREES\nCAVOK\nTP 18 DEGREES CELSIUS\nDP 10\nQNH 1016 HPA 3000 INCHES\nLOW LEVEL WND SHEAR ADVISORIES IN EFFECT ON DEP AND ON FINAL\nAFTER LANDING CONTACT JEJU GND WHEN TURNING ONTO THE RAPID EXIT TAXIWAY TO VACATE RWY\nDO NOT STOP ON THE RAPID EXIT TAXIWAY\nADZ YOU HAVE INFO O\n--------------------\n",
  "ZHCC": "✈️ ZHCC ATIS MONITOR\nUpdate: 2026-04-18 05:39:26\n==============================\n\nZHCC ARR ATIS Z\n2100Z EXP ILSDME APCH\nLDG RWY 12L\nTA 3000\nWIND VRB/1MPS\nVIS 6000M\nNSC\nT 13 /DP 13\nQNH 1013 HPA\nADZ YOU HAVE INFO Z.\n--------------------\nZHCC DEP ATIS Z\n2100Z DEP RWY 12L\nTA 3000\nWIND VRB/1MPS\nVIS 6000M\nNSC\nT 13 /DP 13\nQNH 1013 HPA\nDLV FREQ 118.075\nADZ YOU HAVE INFO Z.\n--------------------\n",
  "RJFF": "✈️ RJFF ATIS MONITOR\nUpdate: 2026-04-18 05:38:13\n==============================\n\nRJFF ARR ATIS G\n1201Z M1200\n(APCH)RNP RWY16L\nLDG RWY 16L\nDEP RWY 16L/16R\nDEP FREQ 127.9\nADZ FUKUOKA APP IF UNA RNP\nAPCH\nINFORM YR LDG RWY TO FUKUOKA\nTWR ON INITIAL CTC.\nM\n171200Z 17006KT 140V200 30KM BKN080AC\n20/12 Q1014/A2995=\nQ/TWO NINE NINE FIVE\nSTP\n--------------------\nRJFF DEP ATIS F\n1135Z M1130\n(APCH)RNP RWY16L\nLDG RWY 16L\nDEP RWY 16L/16R\nDEP FREQ 127.9\nADZ FUKUOKA APP IF UNA\nRNP\nAPCH\nINFORM YR LDG RWY TO\nFUKUOKA\nTWR ON INITIAL CTC.\nM\n171130Z 15006KT 30KM\nFEW050SC BKN080AC\n20/12 Q1014/A2995=\nQ/TWO NINE NINE FIVE\nSTP\n--------------------\n",
  "ZGOW": "✈️ ZGOW ATIS MONITOR\nUpdate: 2026-04-18 05:39:13\n==============================\n\nZGOW ARR ATIS Y\n1500Z EXP ILSDME Z APCH\nLDG RWY 22\nTA 2700 /TRL 3300\nWIND VRB/1MPS\nVIS 9999M\nCLD FEW 1500M\nT 24 /DP 22\nQNH 1011 HPA\nADZ YOU HAVE INFO Y.\n--------------------\nZGOW DEP ATIS D\n1300Z DEP RWY 22\nTA 2700 /TRL 3300\nWIND 150/2MPS VRB BTN 120/ AND 190/\nCAVOK\nT 25 /DP 22\nQNH 1011 HPA\nADZ YOU HAVE INFO D.\n--------------------\n",
  "ZBYN": "✈️ ZBYN ATIS MONITOR\nUpdate: 2026-04-18 05:39:52\n==============================\n\nZBYN ARR ATIS A\n2030Z EXP ILS Z APCH\nLDG RWY 31L\nWIND 080 DEG 2 MPS\nCAVOK\nT 11 /DP 00\nQNH 1013 HPA\nIDENTIFY THE ACTIVE RUNWAY\nADZ YOU HAVE INFO A.\n--------------------\n",
  "ZSFZ": "✈️ ZSFZ ATIS MONITOR\nUpdate: 2026-04-18 05:39:56\n==============================\n\nZSFZ ARR ATIS Z\n1116Z EXP ILSDME Z APCH\nLDG RWY 03\nTA 3000\nWIND 030 DEG 2 MPS\nVIS 4500\nBR\nCLD SCT 150M\nT 20 /DP 20\nQNH 1012 HPA\nSUPPLEMENT INFO /RETS\nTHE NEW EAST RWY IS NOT AVAILABLE,PAY\nATTENTION,DO  NOT LAND ON THE WRONG RWY.\nMISSED APCH:EXPECT FOLLOW PUBLISHED\nPROCEDURE TO 900 METERS ON QNH.\nRWY03 RWYCC 5/5/5 ISSUED AT 1039.ALL\nPARTS WET,NR/NR/NR,100 PCT\nADZ YOU HAVE INFO Z.\n--------------------\nZSFZ DEP ATIS I\n0100Z DEP RWY 03\nTA 3000\nWIND 080 DEG 3 MPS\nVIS 3000\nBR\nCLD FEW 90M /BKN 150M\nT 20 /DP 20\nQNH 1013 HPA\nTHE NEW EAST RWY IS NOT AVAILABLE,PAY\nATTENTION,DO  NOT LAND ON THE WRONG RWY.\nMISSED APCH:EXPECT FOLLOW PUBLISHED\nPROCEDURE TO 900 METERS ON QNH.\nADZ YOU HAVE INFO I.\n--------------------\n",
  "ZBAD": "✈️ ZBAD ATIS MONITOR\nUpdate: 2026-04-18 05:38:22\n==============================\n\nZBAD ARR ATIS Y\n2100Z EXP ILS APCH\nDEPENDENT PARL INSTR APCH\nLDG RWY 35R & 01L\nWIND 030 DEG 1 MPS\nVIS 2500\nRVR RWY 35R TDZ P2000\nRVR RWY 01L TDZ 1400\nBR BCFG\nNSC\nT 12 /DP 11\nQNH 1011 HPA\nADZ YOU HAVE INFO Y.\n--------------------\n",
  "RCMQ": "✈️ RCMQ ATIS MONITOR\nUpdate: 2026-04-18 05:38:13\n==============================\n\nRCMQ ARR ATIS S\n1100Z\nEXPECT I-L-S APPROACH\nRWY 36  ARR/DEP\nWIND 350/10KT\nVIS  8000M\nCLD\nSCT  800FT\nBKN  1400FT\nBKN  4000FT\nT 23 DP 21 QNH 1012HPA\nNOSIG\nINFORM TAIPEI APCH OR\nCHING\n--------------------\nRCMQ DEP ATIS U\n1200Z\nEXPECT I-L-S APPROACH\nRWY 36  ARR/DEP\nWIND 040/06KT\nVIS  7000M\nCLD\nSCT  600FT\nBKN  1200FT\nBKN  4000FT\nT 23 DP 21 QNH 1012HPA\nNOSIG\nINFORM TAIPEI APCH OR\nCHING\n--------------------\n",
  "ZSPD": "✈️ ZSPD ATIS MONITOR\nUpdate: 2026-04-18 05:38:11\n==============================\n\nZSPD ARR ATIS D\n2130Z EXP ILS APCH\nLDG RWY 35L\nWIND RWY 35L TDZ 360/3MPS MID 010/2MPS\nEND 010/2MPS\nVIS RWY 35L TDZ 10000M MID 10000M END\n10000M\nCLD BKN 300M\nT 15 /DP 15\nQNH 1014 HPA\nCAUTION THE BIRDS NEAR THE RUNWAY\nADZ YOU HAVE INFO D.\n--------------------\nZSPD DEP ATIS C\n2100Z DEP RWY 34L\nWIND RWY 34L TDZ 360/4MPS MID 010/4MPS END\n360/3MPS\nVIS RWY 34L TDZ 10000M MID 10000M END 10000M\nCLD BKN 270M\nT 14 /DP 14\nQNH 1014 HPA\nDELIVERY FREQ 118.4\nCAUTION THE BIRDS NEAR THE RUNWAY\nADZ YOU HAVE INFO C.\n--------------------\n",
  "ZUTF": "✈️ ZUTF ATIS MONITOR\nUpdate: 2026-04-18 05:39:56\n==============================\n\nZUTF ARR ATIS A\n2100Z EXP ILSDME APCH\nLDG RWY 02\nTA 3000 /TRL 3600\nWIND RWY 02 TDZ 000/0MPS MID 000/0MPS\nEND 240/1MPS\nCAVOK\nT 14 /DP 14\nQNH 1011 HPA\nDELIVERY FREQUENCY 130.5\nADZ YOU HAVE INFO A.\n--------------------\nZUTF DEP ATIS R\n1700Z DEP RWY 01\nTA 3000 /TRL 3600\nWIND RWY 01 TDZ 000/0MPS MID 010/1MPS\nEND 350/1MPS\nCAVOK\nT 16 /DP 16\nQNH 1013 HPA\nDELIVERY FREQUENCY 118.8\nADZ YOU HAVE INFO R.\n--------------------\n",
  "ZGGG": "✈️ ZGGG ATIS MONITOR\nUpdate: 2026-04-18 05:39:25\n==============================\n\nZGGG ARR ATIS E\n2130Z EXP ILS OR VIS APCH\nLDG RWY 02R\nWIND VRB DEG 1 MPS\nVIS 6000\nNSC\nT 21 /DP 20\nQNH 1011 HPA\nADZ YOU HAVE INFO E.\n--------------------\nZGGG DEP ATIS C\n2030Z DEP RWY 01R\nWIND 010 DEG 2 MPS\nVIS 7000\nNSC\nT 21 /DP 19\nQNH 1010 HPA\nDELIVERY FREQ 121.95\nADZ YOU HAVE INFO C.\n--------------------\n",
  "ZGSZ": "✈️ ZGSZ ATIS MONITOR\nUpdate: 2026-04-18 05:38:11\n==============================\n\nZGSZ ARR ATIS H\n2130Z EXP ILS APCH 33\nEXP ILS OR VIS APCH 34R\nWIND 340/1MPS\nVIS 6000M\nCLD FEW 510M\nT 22 /DP 20\nQNH 1011 HPA\nINDEPENDENT PARALLEL DEPARTURES\nDEPENDENT PARALLEL APPROACHES\nEXPECT RNP ILS DME Z APPROACH\nMISSED APPROACH ALTITUDE SETTING\n1200METERS\nWHEN AIRBORNE CONTACT ZHUHAI APPROACH\nADZ YOU HAVE INFO H.\n--------------------\nZGSZ DEP ATIS H\n2130Z DEP RWY 33 & 34R\nWIND 340/1MPS\nVIS 6000M\nCLD FEW 510M\nT 22 /DP 20\nQNH 1011 HPA\nDELIVERY FREQ 118.45\nINDEPENDENT PARALLEL DEPARTURES\nDEPENDENT PARALLEL APPROACHES\nEXPECT RNP ILS DME Z APPROACH\nMISSED APPROACH ALTITUDE SETTING 1200METERS\nWHEN AIRBORNE CONTACT ZHUHAI APPROACH\nADZ YOU HAVE INFO H.\n--------------------\n",
  "ZSNB": "✈️ ZSNB ATIS MONITOR\nUpdate: 2026-04-18 05:39:37\n==============================\n\nZSNB ARR ATIS Q\n1200Z EXP ILSDME Z APCH\nLDG RWY 31\nWIND 040 DEG 3 MPS 010V080 DEG\nVIS 7000\nCLD FEW 990M\nT 19 /DP 15\nQNH 1014 HPA\nADZ YOU HAVE INFO Q.\n--------------------\nZSNB DEP ATIS P\n1100Z DEP RWY 31\nWIND 050 DEG 3 MPS 010V080 DEG\nVIS 7000\nCLD SCT 900M\nT 20 /DP 16\nQNH 1012 HPA\nADZ YOU HAVE INFO P.\n--------------------\n",
  "RCTP": "✈️ RCTP ATIS MONITOR\nUpdate: 2026-04-18 05:38:51\n==============================\n\nRCTP ARR ATIS T\n2130Z\nEXP ILS APCH\nRWY05L ARR/DEP. RWY05R CLSD BTN 1700Z AND\n2230Z FOR INSPECTION.\nWIND 130/04KT\nVIS  10 KM OR MORE\nCLD\nFEW  1500FT\nBKN  16000FT\nT 23 DP 21 QNH 1010HPA\nNOSIG\nINFORM TAIPEI APCH OR TAIPEI TOWER ON INITIAL\nCONTACT\nYOU HAVE INFORMATION T\n--------------------\n",
  "RJAA": "✈️ RJAA ATIS MONITOR\nUpdate: 2026-04-18 05:38:14\n==============================\n\nRJAA ARR ATIS D\n2135Z M2130\n(APCH)ILS Y RWY16L\nLDG RWY 16L\nDEP RWY 16R\nDEP FREQ 124.2.\nTWY A1 CLSD.\nM\n172130Z 05003KT 360V090\n20KM FEW030CU\nBKN040SC 13/10\nQ1018/A3008=\nQ/THREE ZERO ZERO EIGHT\nSTP\n--------------------\nRJAA DEP ATIS M\n1318Z M1300\n(APCH)ILS Y RWY16R/ILS Y RWY16L\nUSING RWY 16R/16L\nDEP FREQ 124.2.\nTWY A1 CLSD.\nPARL APCHS INPR.\nRWY 16L/34R WILL BE CLSD FM 1410.\nM\n171300Z 30003KT 25KM BKN/// 11/07\nQ1021/A3016=\nQ/THREE ZERO ONE SIX\nSTP\n--------------------\n"
}