{
  "VTBS": "✈️ VTBS ATIS MONITOR\nUpdate: 2026-04-29 10:36:52\n==============================\n\nVTBS ARR ATIS A\n0230Z VTBS ARR ATIS A\n0231Z EXP ILS Z APCH ARR RWY 19 OR RNP APCH\nRWY 20R\n,\n,PILOT SHALL ADZ BKK APCH ON INITIAL CTC IF\nUNA TO CONDUCT RNP APCH DUE TO\nOPERATIONAL CONSTRAINT\n0230Z WIND 250/5KT VRB BTN 200/ AND 280/ VIS\n10KM CLD FEW 2000FT T34 DP22 QNH\n1010HPA TREND NOSIG\nADZ BKK APCH ON INITIAL CONTACT THAT YOU HAVE\nINFO A\n--------------------\nVTBS DEP ATIS M\n0200Z VTBS DEP ATIS M\n0201Z SIMULTANEOUS INDEPENDENT PARL DEP IN\nPROGRESS\nDEP RWY 20L OR DEP RWY 19\n,\n,AFT AIRBORNE ALL DEPARTING ACFT SHALL CTC\n119.25\n0200Z WIND 230/5KT VRB BTN 160/ AND 260/ VIS\n10KM CLD FEW 2000FT T33 DP22 QNH\n1010HPA TREND NOSIG\nADZ GND WHEN INITIAL CONTACT YOU HAVE INFO M\n--------------------\n",
  "ZHHH": "✈️ ZHHH ATIS MONITOR\nUpdate: 2026-04-29 10:37:44\n==============================\n\nZHHH ARR ATIS L\n2300Z EXP ILSDME APCH\nLDG RWY 05L\nTA 3000\nWIND 010/3MPS VRB BTN 330/ AND 040/\nCAVOK\nT 14 /DP 13\nQNH 1020 HPA\nSEGREGATED OPERATION\nRNAV ARR IS AVAIL\nADZ YOU HAVE INFO L.\n--------------------\nZHHH DEP ATIS C\n0000Z DEP RWY 04\nTA 3000\nWIND 010/3MPS VRB BTN 310/ AND 040/\nCAVOK\nT 14 /DP 13\nQNH 1021 HPA\nSEGREGATED OPERATION\nRNAV DEP IS AVAIL\nADZ YOU HAVE INFO C.\n--------------------\n",
  "ZSOF": "✈️ ZSOF ATIS MONITOR\nUpdate: 2026-04-29 10:36:13\n==============================\n\nZSOF ARR ATIS D\n0100Z EXP ILS Z APCH\nLDG RWY 15\nWIND 100 DEG 5 MPS 060V120 DEG\nVIS 9999\nCLD FEW 600M\nT 13 /DP 10\nQNH 1023 HPA\nTRL 3600\nADZ YOU HAVE INFO D.\n--------------------\n",
  "WMKK": "✈️ WMKK ATIS MONITOR\nUpdate: 2026-04-29 10:35:57\n==============================\n\nWMKK ARR ATIS M\n0204Z WMKK ARR INFO M.\nTIME 0200.\nINDEPENDENT PARALLEL APPROACHES FOR RWY 14 L\nAND 15 ARE IN PROGRESS.\nEXP RNAV / ILS APCH FOR RWY 14 LEFT.\nEXP RNAV / ILS APCH FOR RWY 15.\nWIND RWY 14L 330 DEG, 3 KT, VRB BTN 290 AND\n080 DEG.\nWIND RWY 15 010 DEG, 3 KT.\nVIS RWY 14L TDZ NOT AVBL.\nVIS RWY 15 TDZ NOT AVBL.\nCLD FEW 1800 FT.\nT 31.\nDP 25.\nQNH 1009.\nNOSIG.\nAT FIRST CONTACT WITH LUMPUR RADAR, NOTIFY\nRCPT OF M\n--------------------\nWMKK DEP ATIS X\n1404Z WMKK DEP INFO X.\nTIME 1400.\nSINGLE RWY OPS IN PROGRESS.\nRWY 14 RIGHT.\nWIND RWY 14R 050 DEG, 6 KT, VRB BTN 360 AND 080 DEG.\nVIS RWY 14R TDZ NOT AVBL.\nWX FBL TSRA.\nCLD FEW 900 FT, CLD FEW CB 1700 FT, CLD SCT 3000 FT.\nT 27.\nDP 25.\nQNH 1008.\nNOSIG.\nALL DEP ACFT TO CONTACT LUMPUR DEP AT 135 DECIMAL 25 MHZ WHEN ABN.\nAT FIRST CONTACT WITH LUMPUR GROUND, NOTIFY RCPT OF X\n--------------------\n",
  "ZGNN": "✈️ ZGNN ATIS MONITOR\nUpdate: 2026-04-29 10:35:59\n==============================\n\nZGNN ARR ATIS O\n0132Z EXP ILS-W APCH\nLDG RWY 05\nSFC COND & BA NOTICE:RWYCC 05 5/5/5\nISSUED AT 2120Z ALL PARTS WET NR 100PCT\nTRL 3600\nWIND RWY 05 TDZ 350/3MPS MID 350/5MPS\nEND 340/4MPS\nVIS RWY 05 TDZ 9999M MID 9999M END 9999M\nRVR RWY 05 TDZ P2000M MID P2000M END\nP2000M\nCLD OVC 990M\nT 21 /DP 17\nQNH 1014 HPA QFE RWY 05 TDZ 999 HPA END\n999 HPA\nMILITARY ACTIVITY\nIN CASE OF MISSED APCH,CLIMB TO 1200\nMETERS ON QFE\nADZ YOU HAVE INFO O.\n--------------------\nZGNN DEP ATIS Q\n0201Z DEP RWY 05\nTRL 3600\nWIND RWY 05 TDZ 170/1MPS\nMID 180/2MPS END\n150/2MPS\nVIS RWY 05 TDZ 8000M MID\n9999M END 7000M\nRVR RWY 05 TDZ P2000M\nMID P2000M END P2000M\nCLD FEW 390M\nT 26 /DP 22\nQNH 1011 HPA QFE RWY 05\nTDZ 996 HPA END 996 HPA\nINTERSECTION TAKE OFF\nVIA B3\nADZ YOU HAVE INFO Q.\n--------------------\n",
  "VVNB": "✈️ VVNB ATIS MONITOR\nUpdate: 2026-04-29 10:35:59\n==============================\n\nVVNB ARR ATIS M\n0200Z VVNB INFO M 0200Z. ILS X RWY 11L. DPTG\nRWY 11R AND ARR RWY 11L .. 0200Z. WIND\n340/4KT VIS 10KM CLD FEW 3000FT BKN 4600FT\nT21 DP18 QNH 1015HPA TREND NOSIG. RWY\nCONDITION REPORT 5 5 5.. ADZ ON INITIAL CTC\nYOU HAVE INFO M.\n--------------------\nVVNB DEP ATIS H\n0001Z VVNB INFO H 0001Z. ILS X RWY 11L. DPTG RWY 11R AND ARR RWY 11L .. 0001Z. WIND 340/9KT VIS 10KM FBL RA CLD FEW 2700FT BKN 3900FT T21 DP19 QNH 1013HPA TREND NOSIG. ADZ ON INITIAL CTC YOU HAVE INFO H.\n--------------------\n",
  "ZUGY": "✈️ ZUGY ATIS MONITOR\nUpdate: 2026-04-29 10:37:04\n==============================\n\nZUGY ARR ATIS Y\n0123Z EXP RNAV ILS APCH\nLDG RWY 01R\nTA 3000 /TRL 3600\nWIND 060/4MPS\nVIS 9999M\nCLD SCT 390M /OVC 990M\nT 11 /DP 10\nQNH 1022 HPA\nDEPARTURE AIRCRAFT ARE DEEMED TO ACCEPT\nA11 INTERSECTION DEPARTURE,IF UNABLE TO\nCOMPLY,PLEASE NOTIFY ATC PROMPTLY\nTHERE IS LIGHT TO MODERATE TURBULENCE\nABOVE 3000 METERS ON QNH\nADZ YOU HAVE INFO Y.\n--------------------\nZUGY DEP ATIS B\n1200Z DEP RWY 19L\nTA 3000 /TRL 3600\nWIND 100/2MPS VRB BTN 070/ AND 150/\nVIS 9999M\nCLD FEW 1380M\nT 14 /DP 12\nQNH 1014 HPA\nTHERE IS LIGHT TO MODERATE TURBULENCE\nABOVE 2500 METERS ON QNH\nADZ YOU HAVE INFO B.\n--------------------\n",
  "ZUUU": "✈️ ZUUU ATIS MONITOR\nUpdate: 2026-04-29 10:35:59\n==============================\n\nZUUU ARR ATIS U\n0200Z EXP RNAV ILS APCH\nLDG RWY 02R\nTA 3000 /TRL 3600\nWIND RWY 02R TDZ 210/2MPS MID 330/1MPS\nEND 280/1MPS\nVIS RWY 02R TDZ 9999M MID 9999M END\n9999M\nRVR RWY 02R TDZ P2000M MID P2000M END\nP2000M\nCLD FEW 600M /SCT 990M\nT 20 /DP 12\nQNH 1022 HPA\nADZ YOU HAVE INFO U.\n--------------------\nZUUU DEP ATIS W\n0231Z DEP RWY 02L\nTA 3000 /TRL 3600\nWIND RWY 02L TDZ\n170/1MPS MID 130/1MPS\nEND 230/1MPS\nVIS RWY 02L TDZ 9999M\nMID 9999M END 9999M\nRVR RWY 02L TDZ P2000M\nMID P2000M END P2000M\nCLD BKN 780M\nT 21 /DP 12\nQNH 1022 HPA\nRWY STATUS 02L  DEP FREQ\n124.85 DLV FREQ 121.75\nADZ YOU HAVE INFO W.\n--------------------\n",
  "RKSI": "✈️ RKSI ATIS MONITOR\nUpdate: 2026-04-29 10:35:58\n==============================\n\nRKSI ARR ATIS W\n0230Z\nEXP SIMUL PARALLEL ILS APCH RWY 33R AND ILS APCH RWY 34L\nEXP LDG RWY INFO FROM SEOUL APP\nWIND 300/4KT\nCAVOK\nT 17\nDP 6\nQNH 1020\nCAUTION BIRD ACTIVITY\nEXP REBIT 1Y OLMEN 1Y GUKDO 2E KARBU 2E ARRIVAL\nGPS SIGNAL UNRELIABLE DUE TO GPS INTERFERENCE IN SEOUL APCH AREA\n--------------------\n",
  "ZGKL": "✈️ ZGKL ATIS MONITOR\nUpdate: 2026-04-29 10:35:58\n==============================\n\nZGKL ARR ATIS S\n0212Z EXP ILSDME APCH\nLDG RWY 01\nTA 3000\nWIND 060 DEG 4 MPS\nVIS 9999\nCLD SCT 1080M /BKN 1500M\nT 18 /DP 14\nQNH 1018 HPA\nMILITARY ACTIVITY\nRWY 01 RWYCC 5/5/5 ISSUED AT 0115 ALL\nPARTS WET NR 100PCT\nADZ YOU HAVE INFO S.\n--------------------\nZGKL DEP ATIS N\n1300Z DEP RWY 01\nTA 3000\nWIND VRB DEG 1 MPS\nVIS 9999\nCLD OVC 1380M\nT 15 /DP 13\nQNH 1013 HPA\nADZ YOU HAVE INFO N.\n--------------------\n",
  "VHHH": "✈️ VHHH ATIS MONITOR\nUpdate: 2026-04-29 10:36:00\n==============================\n\nVHHH ARR ATIS E\n0206Z\nARRIVALS, RWY 25R/L.\nEXP RNAV TRANSITION TO ILS  APCH, RWY 25R.\nEXP ILS  APCH, RWY 25L.\nRNP APCH IS AVBL ON REQ, RWY 25L.\nCAUTION POSSIBLE GP FLUCTUATION RWY 25L.\nWIND RWY 25L VRB05KT RWY 25R VRB05KT VIS RWY\n25L 10KM RWY 25R 10KM FBL SHRA CLD FEW CB\n1200FT SCT 2200FT T28 DP23 QNH 1011HPA TREND\nTEMPO VRB20KT MAX30 VIS 2500M MOD TSRA HVY\nSHRA CLD FEW CB 800FT SCT 1500FT= ACKNOWLEDGE\nINFO E ON FIRST CTC WITH APP.\n--------------------\n",
  "VTBD": "✈️ VTBD ATIS MONITOR\nUpdate: 2026-04-29 10:36:01\n==============================\n\nVTBD ARR ATIS I\n1002Z EXP ILS\nZ APCH RWY 21 , RWY IN USE 21\n04260803 21R 5/5/5 100/100/100\nNR/NR/NR WET/WET/WET 04260806\n21L 5/5/5 100/100/100 NR/NR/NR\nWET/WET/WET 1000Z WIND 170/5KT\nVIS 10KM CLD FEW 2000FT SCT\n3500FT T30 DP26 QNH 1007HPA\nTREND NOSIG ADZ CONTROLLER\nWHEN INITIAL CONTACT YOU HAVE\nINFO I\n--------------------\nVTBD DEP ATIS X\n0301Z\nRWY IN USE 21 0300Z WIND\n210/6KT VIS 10KM CLD FEW\n2000FT T34 DP24 QNH\n1010HPA TREND NOSIG ADZ\nCONTROLLER WHEN INITIAL\nCONTACT YOU HAVE INFO X\n--------------------\n",
  "VVDN": "✈️ VVDN ATIS MONITOR\nUpdate: 2026-04-29 10:35:58\n==============================\n\nVVDN ARR ATIS B\n1732Z VVDN INFO B 1732Z. ILS VICTOR APPROACH 35L.. DPTG RWY 35R.. 1732Z. WIND 210/04KT CAVOK T24 DP21 QNH 1008HPA TREND NOSIG. DUE WORK IN PROGRESS ADVISE ECHO2 FOR DEPARTURE RUNWAY 35R. ADZ ON INITIAL CTC YOU HAVE INFO. B.\n--------------------\nVVDN DEP ATIS G\n0803Z VVDN INFO G 0803Z. ILS VICTOR\nAPPROACH 35L.. DPTG RWY 35R.. 0803Z.\nWIND 280/03KT CAVOK T28 DP21 QNH\n1007HPA TREND NOSIG. DUE WORK IN\nPROGRESS ADVISE ECHO2 FOR DEPARTURE\nRUNWAY 35R. ADZ ON INITIAL CTC YOU HAVE\nINFO. G.\n--------------------\n",
  "ZBTJ": "✈️ ZBTJ ATIS MONITOR\nUpdate: 2026-04-29 10:36:49\n==============================\n\nZBTJ ARR ATIS G\n0200Z EXP ILSDME APCH\nLDG RWY 34L\nWIND 320 DEG 3 MPS 280V350 DEG\nCAVOK\nT 20 /DP M01\nQNH 1021 HPA\nSINGLE RUNWAY OPERATION\nIF MISSED APPROACH TRACK EXTENDED\nCENTERLINE MAINTAIN 600 METERS,DUE TO\nMILITARY ACTIVITY\nREQUEST PDC ON GROUND 121.95\nADZ YOU HAVE INFO G.\n--------------------\nZBTJ DEP ATIS O\n0300Z DEP RWY 34R\nWIND VRB DEG 2 MPS\nVIS 9999\nCLD BKN 1200M /FEW TCU 1200M\nT 17 /DP 04\nQNH 1021 HPA\nSINGLE RUNWAY OPERATION\nIF MISSED APPROACH TRACK EXTENDED\nCENTERLINE MAINTAIN 600 METERS,DUE TO\nMILITARY ACTIVITY\nREQUEST PDC ON GROUND 121.95\nADZ YOU HAVE INFO O.\n--------------------\n",
  "ZBAA": "✈️ ZBAA ATIS MONITOR\nUpdate: 2026-04-29 10:36:07\n==============================\n\nZBAA ARR ATIS V\n0230Z EXP ILS APCH\nDEPENDENT PARL INSTR APCH\nLDG RWY 36L & 36R & 01\nWIND 310 DEG 3 MPS 260V360 DEG\nCAVOK\nT 21 /DP M02\nQNH 1021 HPA\nVISUAL APPROACH IS IN PROGRESS.\nADZ YOU HAVE INFO V.\n--------------------\nZBAA DEP ATIS O\n2300Z DEP RWY 36L & 36R & 01\nWIND 360 DEG 3 MPS\nCAVOK\nT 12 /DP 05\nQNH 1022 HPA\nRWY INDEPENDENT PARALLEL DEP\nVISUAL APPROACH IS IN\nPROGRESS.\nADZ YOU HAVE INFO O.\n--------------------\n",
  "ZSHC": "✈️ ZSHC ATIS MONITOR\nUpdate: 2026-04-29 10:36:08\n==============================\n\nZSHC ARR ATIS U\n0230Z EXP ILS OR VIS APCH\nLDG RWY 06 & 07\nWIND RWY 06 TDZ 040/4MPS MID 050/4MPS\nVRB BTN 010/ AND 080/ END 030/5MPS\nRWY 07 TDZ 040/6MPS MID 040/5MPS END\n050/4MPS\nVIS RWY 06 TDZ 6000M MID 6000M END 7000M\nVIS RWY 07 TDZ 6000M MID 9000M END 8000M\nFBL SHRA BR\nCLD BKN 270M /BKN 600M\nT 12 /DP 10\nQNH 1022 HPA\nEXPECT MISSED APPROACH ALTITUDE SETTING\n1200METERS\nRWY 06/07 RWYCC 5/5/5 ISSUED AT 2132 ALL\nPARTS WET NR 100 PCT\nADZ YOU HAVE INFO U.\n--------------------\nZSHC DEP ATIS T\n0200Z DEP RWY 06 & 07\nWIND RWY 06 TDZ 050/4MPS MID 050/4MPS\nEND 030/4MPS\nRWY 07 TDZ 050/7MPS MID 040/7MPS END\n040/6MPS\nVIS RWY 06 TDZ 6000M MID 6000M END 7000M\nVIS RWY 07 TDZ 5000M MID 7000M END 7000M\nFBL SHRA BR\nCLD BKN 270M /BKN 600M\nT 11 /DP 10\nQNH 1022 HPA\nEXPECT MISSED APPROACH ALTITUDE SETTING\n1200METERS\nRWY 06/07 RWYCC 5/5/5 ISSUED AT 2132 ALL\nPARTS WET NR 100 PCT\nADZ YOU HAVE INFO T.\n--------------------\n",
  "RCKH": "✈️ RCKH ATIS MONITOR\nUpdate: 2026-04-29 10:35:58\n==============================\n\nRCKH ARR ATIS P\n2100Z\nEXPECT ILS  APPROACH\nRWY 09  ARR/DEP\nTAXIWAY ECHO,  TAXIWAY SIERRA THREE,  TAXIWAY\nALPHA BETWEEN RUNWAY AND PARKING BAY HOTEL 1\nCLOSED, DUE TO CONSTRUCTION WORK. FROM 0 2 5 0\nZULU TO 0 3 3 0 ZULU RUNWAY CLOSED. ALL\nTAKE-OFF AND LANDING SUSPENDED DUE TO\nCONSTRUCTION WORK.\nWIND 080/01KT\nVIS  10 KM OR MORE\nCLD\nFEW  1600FT\nSCT  20000FT\nT 24 DP 19 QNH 1009HPA\nNOSIG\nCAUTION BIRD ACTIVITY IN VINCINITY OF\nAERODROME.\nINFORM KAO-HSIUN APCH OR KAO-HSIUN TOWER ON\nINITIAL CONTACT\nYOU HAVE INFORMATION P\n--------------------\nRCKH DEP ATIS S\n0700Z\nEXPECT ILS  APPROACH\nRWY 09  ARR/DEP\nTAXIWAY ECHO,  TAXIWAY SIERRA THREE,\nTAXIWAY ALPHA BETWEEN RUNWAY AND PARKING\nBAY HOTEL 1 CLOSED, DUE TO CONSTRUCTION\nWORK.\nWIND 230/\n--------------------\n",
  "ZUCK": "✈️ ZUCK ATIS MONITOR\nUpdate: 2026-04-29 10:37:22\n==============================\n\nZUCK ARR ATIS Y\n0100Z EXP ILSDME APCH\nDEPENDENT PARL INSTR APCH\nLDG RWY 02L & 03R\nTA 3000 /TRL 3600\nWIND 050/3MPS VRB BTN 020/ AND 080/\nVIS 9999M\nCLD FEW 240M /SCT 600M /OVC 990M\nT 16 /DP 16\nQNH 1022 HPA\nRWY 02L/02R/03L/03R RWYCC 5/5/5 ALL\nPARTS WET NR 100PCT\nRNAV IS AVAIL\nADZ YOU HAVE INFO Y.\n--------------------\nZUCK DEP ATIS W\n2300Z DEP RWY 02R & 03L\nTA 3000 /TRL 3600\nWIND 010/4MPS\nVIS 7000M\n-SHRA\nCLD FEW 120M /SCT 480M /OVC 990M\nT 13 /DP 13\nQNH 1021 HPA\nRWY 02L/02R/03L/03R RWYCC 5/5/5 ALL\nPARTS WET NR 100PCT\nRNAV IS AVAIL\nADZ YOU HAVE INFO W.\n--------------------\n",
  "WSSS": "✈️ WSSS ATIS MONITOR\nUpdate: 2026-04-29 10:35:57\n==============================\n\nWSSS ARR ATIS P\n0200Z\nMETREPORT 0200Z\nILS APCHRWY 02L\nSIMUL INDEPENDENT ILS\nAND VISUAL APPROACHES\nARE BEING CONDUCTED ON\nRWY 02.\nRWY 02C/20C RAPID EXIT\nTAXIWAY INDICATOR\nLIGHTS OFF\nWIND 010/ 06KT VRB\nBTN350 AND080\nVIS 10KM\nCLD SCT 1800FT\nT31 DP26\nQNH 1010HPA\nNOSIG\nACK ATIS P\n--------------------\nWSSS DEP ATIS U\n0200Z\nMETREPORT 0200Z RWY 02C\nSIMUL INDEPENDENT ILS AND\nVISUAL APPROACHES ARE BEING\nCONDUCTED ON RWY 02.\nWIND 050/ 04KT VRB BTN350\nAND070\nVIS 10KM\nCLD SCT 1800FT\nT31 DP26\nQNH 1010HPA\nNOSIG\nDEP,INITIAL CMB 3000FT\nACK ATIS U\n--------------------\n",
  "RJBB": "✈️ RJBB ATIS MONITOR\nUpdate: 2026-04-29 10:35:57\n==============================\n\nRJBB ARR ATIS P\n0236Z M0230\n(APCH)ILS Z RWY06R\nLDG RWY 06R\nDEP RWY 06L\nDEP FREQ 119.2.\nM\n290230Z 05006KT 20KM FEW025CU BKN120AC\nBKN150AC 19/13 Q1016/A3000=\nQ/THREE ZERO ZERO ZERO\nSTP\n--------------------\nRJBB DEP ATIS N\n0145Z M0130\n(APCH)ILS Z RWY06R\nLDG RWY 06R\nDEP RWY 06L\nDEP FREQ 119.2.\nM\n290130Z 04007KT 20KM FEW025CU\nSCT100AC\nBKN150AC 18/12 Q1016/A3000=\nQ/THREE ZERO ZERO ZERO\nSTP\n--------------------\n",
  "ZSAM": "✈️ ZSAM ATIS MONITOR\nUpdate: 2026-04-29 10:36:20\n==============================\n\nZSAM ARR ATIS T\n0200Z EXP ILSDME APCH\nLDG RWY 05\nTA 3000\nWIND RWY 05 TDZ 040/2MPS END 050/2MPS\nVIS RWY 05 TDZ 10000M MID 10000M END\n10000M\nCLD FEW 240M /FEW CB 600M /BKN 780M\nT 23 /DP 21\nQNH 1012 HPA\nRWY 05 RWYCC 5/5/5 ISSUED AT 0056\nWET/WET/WET DPT NR/NR/NR COV\n100PCT/100PCT/100PCT\nIN CASE MISSED-APPROACH,EXPECT CONTINUE\nRUNWAY HEADING,INITIAL ALTITUDE 900\nMETERS ON QNH.IF RADIO FAILURE FOLLOW\nMISSED-APPROACH AS PUBLISHED.\nADZ YOU HAVE INFO T.\n--------------------\nZSAM DEP ATIS R\n0000Z DEP RWY 05\nTA 3000\nWIND RWY 05 TDZ 090/3MPS END 110/3MPS\nVIS RWY 05 TDZ 10000M MID 10000M END 10000M\nFBL SHRA\nCLD FEW 120M /FEW CB 600M /OVC 780M\nT 22 /DP 20\nQNH 1012 HPA\nRWY 05 RWYCC 5/5/5 ISSUED AT 0056 WET/WET/WET\nDPT NR/NR/NR COV 100PCT/100PCT/100PCT\nIN CASE MISSED-APPROACH,EXPECT CONTINUE RUNWAY\nHEADING,INITIAL ALTITUDE 900 METERS ON QNH.IF\nRADIO FAILURE FOLLOW MISSED-APPROACH AS\nPUBLISHED.\nADZ YOU HAVE INFO R.\n--------------------\n",
  "ZSQD": "✈️ ZSQD ATIS MONITOR\nUpdate: 2026-04-29 10:37:19\n==============================\n\nZSQD ARR ATIS D\n2100Z EXP ILSDME APCH\nLDG RWY 34\nTA 3000 /TRL 3600\nWIND VRB/1MPS\nVIS 6000M\nNSC\nT 07 /DP 05\nQNH 1022 HPA\nVISUAL APPROACH OPERATION IN\nPROGRESS.\nWHEN READY CONTACT QINGDAO\nTOWER ON 118.7\nRUNWAY 34,IF MISSED\nAPPROACH,EXPECT FOLLOW THE\nSTANDARD MISSED APPROACH\nPROCEDURE,CLIMB TO 900M ON QNH\nOR BY ATC\nCAUTION MAYBE THERE IS A FLOCK\nOF BIRDS IN THE VICINITY OF\nAIRPORT\nADZ YOU HAVE INFO D.\n--------------------\n",
  "RKPC": "✈️ RKPC ATIS MONITOR\nUpdate: 2026-04-29 10:35:57\n==============================\n\nRKPC ARR ATIS K\n0111Z\nEXP ILS Z RWY 07 APP\nDEP RWY 07\nDEP FREQ WILL BE 121.200\nWND 310 AT 4 KTS\nVARIABLE BTWN 270 DEGREES AND 350 DEGREES\nVIS 10 KM OR MORE\nCLD\nOVERCAST 7 THOUSAND FT\nTP 15 DEGREES CELSIUS\nDP 05\nQNH 1020 HPA 3012 INCHES\nGRASS CUTTING IN PROGRESS L SIDE OF RWY 07\nAFTER LANDING CONTACT JEJU GND WHEN TURNING ONTO THE RAPID EXIT TAXIWAY TO VACATE RWY\nDO NOT STOP ON THE RAPID EXIT TAXIWAY\nADZ YOU HAVE INFO K\n--------------------\nRKPC DEP ATIS N\n0700Z\nEXP RNP Y RWY 25 APP\nDEP RWY 25 AND 31 AVAILABLE\nDEP FREQ WILL BE 121.200\nWND 330 AT 10 KTS\nVARIABLE BTWN 280 DEGREES AND 340 DEGREES\nVIS 10 KM OR MORE\nCLD\nFEW 3 THOUSAND FT\nBROKEN 14 THOUSAND FT\nTP 14 DEGREES CELSIUS\nDP 08\nQNH 1017 HPA 3003 INCHES\nIF YOU WANT TO EXECUTE RNP Z RWY 25 APP, REQUEST ATC ON INITIAL CONTACT\nHIGH INTENSITY RWY OPERATION IN FORCE, MIN RWY OCCUPANCY TIME REQUIRED\nAFTER LANDING CONTACT JEJU GND WHEN TURNING ONTO THE RAPID EXIT TAXIWAY TO VACATE RWY\nDO NOT STOP ON THE RAPID EXIT TAXIWAY\nADZ YOU HAVE INFO N\n--------------------\n",
  "ZHCC": "✈️ ZHCC ATIS MONITOR\nUpdate: 2026-04-29 10:36:08\n==============================\n\nZHCC ARR ATIS B\n0100Z EXP ILS OR VIS APCH\nLDG RWY 12R\nTA 3000\nWIND 050/4MPS VRB BTN 360/ AND 070/\nCAVOK\nT 17 /DP 05\nQNH 1024 HPA\nADZ YOU HAVE INFO B.\n--------------------\nZHCC DEP ATIS Y\n2329Z DEP RWY 12L\nTA 3000\nWIND 030/3MPS\nCAVOK\nT 15 /DP 07\nQNH 1023 HPA\nDLV FREQ 118.075\nADZ YOU HAVE INFO Y.\n--------------------\n",
  "RJFF": "✈️ RJFF ATIS MONITOR\nUpdate: 2026-04-29 10:36:09\n==============================\n\nRJFF ARR ATIS J\n0204Z M0200\n(APCH)RNP RWY16L\nLDG RWY 16L\nDEP RWY 16L/16R\nDEP FREQ 127.9\nADZ FUKUOKA APP IF UNA RNP\nAPCH\nINFORM YR LDG RWY TO FUKUOKA\nTWR ON INITIAL CTC.\nM\n290200Z 36008KT 330V040 25KM FEW020CU\nSCT030CU BKN130AC 18/11\nQ1017/A3005=\nQ/THREE ZERO ZERO FIVE\nSTP\n--------------------\nRJFF DEP ATIS K\n0233Z M0230\n(APCH)RNP RWY16L\nLDG RWY 16L\nDEP RWY 16L/16R\nDEP FREQ 127.9\nADZ FUKUOKA APP IF UNA RNP\nAPCH\nINFORM YR LDG RWY TO FUKUOKA\nTWR ON INITIAL CTC.\nM\n290230Z 36009KT 330V030 30KM\nFEW025CU\nBKN130AC 18/10 Q1017/A3005=\nQ/THREE ZERO ZERO FIVE\nSTP\n--------------------\n",
  "ZGOW": "✈️ ZGOW ATIS MONITOR\nUpdate: 2026-04-29 10:35:58\n==============================\n\nZGOW ARR ATIS M\n0000Z EXP ILSDME Z APCH\nLDG RWY 04\nTA 2700 /TRL 3300\nWIND 070/2MPS\nVIS 4000M\nBR\nCLD SCT 390M\nT 24 /DP 23\nQNH 1011 HPA\nRWY 04 RWYCC 5/5/5 ISSUED AT 2200 ALL\nPARTS WET NR 100PCT\nADZ YOU HAVE INFO M.\n--------------------\n",
  "ZBYN": "✈️ ZBYN ATIS MONITOR\nUpdate: 2026-04-29 10:35:59\n==============================\n\nZBYN ARR ATIS O\n0200Z EXP ILS Z APCH\nLDG RWY 31L\nWIND VRB DEG 1 MPS\nCAVOK\nT 16 /DP 01\nQNH 1024 HPA\nIDENTIFY THE ACTIVE RUNWAY\nADZ YOU HAVE INFO O.\n--------------------\nZBYN DEP ATIS S\n0030Z DEP RWY 31L\nWIND 360 DEG 8 MPS\nVIS 8000\nNSC\nT 16 /DP M11\nQNH 1017 HPA\nIDENTIFY THE ACTIVE\nRUNWAY\nADZ YOU HAVE INFO S.\n--------------------\n",
  "ZSFZ": "✈️ ZSFZ ATIS MONITOR\nUpdate: 2026-04-29 10:37:30\n==============================\n\nZSFZ ARR ATIS D\n1300Z EXP ILSDME Z APCH\nLDG RWY 03\nTA 3000\nWIND 020 DEG 3 MPS 340V040 DEG\nCAVOK\nT 22 /DP 20\nQNH 1013 HPA\nTHE NEW EAST RWY IS NOT AVAILABLE,PAY\nATTENTION,DO  NOT LAND ON THE WRONG RWY.\nMISSED APCH:EXPECT FOLLOW PUBLISHED\nPROCEDURE TO 900 METERS ON QNH.\nADZ YOU HAVE INFO D.\n--------------------\nZSFZ DEP ATIS J\n0000Z DEP RWY 03\nTA 3000\nWIND VRB DEG 1 MPS\nVIS 5000\nBR\nNSC\nT 21 /DP 19\nQNH 1013 HPA\nTHE NEW EAST RWY IS NOT AVAILABLE,PAY\nATTENTION,DO  NOT LAND ON THE WRONG RWY.\nMISSED APCH:\n--------------------\n",
  "ZBAD": "✈️ ZBAD ATIS MONITOR\nUpdate: 2026-04-29 10:35:57\n==============================\n\nZBAD ARR ATIS A\n0230Z EXP ILS APCH\nDEPENDENT PARL INSTR APCH\nLDG RWY 35L & 01L\nWIND VRB DEG 2G7 MPS\nCAVOK\nT 22 /DP M05\nQNH 1021 HPA\nVISUAL APPROACH IS IN PROGRESS\nADZ YOU HAVE INFO A.\n--------------------\nZBAD DEP ATIS X\n0130Z DEP RWY 35R & 11L\nWIND VRB DEG 2 MPS\nCAVOK\nT 20 /DP M03\nQNH 1022 HPA\nRTE VIA OMD/PEG CTC FREQ 122.825 OTHERS\nCTC FREQ 121.875\nVISUAL APPROACH IS IN PROGRESS\nADZ YOU HAVE INFO X.\n--------------------\n",
  "RCMQ": "✈️ RCMQ ATIS MONITOR\nUpdate: 2026-04-29 10:36:11\n==============================\n\nRCMQ ARR ATIS V\n1200Z\nEXPECT I-L-S APPROACH\nRWY 36  ARR/DEP\nPAPI  IS OUT , RUNWAY\nGUARD  LIGHTS OUT\nWIND 360/04KT\nVIS  10 KM OR MORE\nCLD\nFEW  1200FT\nT 23 DP 16 QNH 1012HPA\nNOSIG\nIN\n--------------------\n",
  "ZSPD": "✈️ ZSPD ATIS MONITOR\nUpdate: 2026-04-29 10:37:12\n==============================\n\nZSPD ARR ATIS Q\n0230Z EXP ILS APCH\nINDEPENDENT PARL INSTR APCH\nLDG RWY 35L & 34R\nWIND RWY 35L TDZ 030/8MPS MID 040/8MPS\nEND 050/8MPS\nRWY 34R TDZ 040/9MPS MID 000/0MPS END\n050/9MPS\nVIS RWY 35L TDZ 2200M MID 10000M END\n10000M\nVIS RWY 34R TDZ 10000M MID 10000M END\n10000M\nFBL RA\nCLD BKN 330M\nT 12 /DP 10\nQNH 1021 HPA\nCAUTION THE BIRDS NEAR THE RUNWAY\nRWY 35R/35L/34R/34L RWYCC 5/5/5 ISSUED\nAT 0138 WET/WET/WET DPT NR/NR/NR COV\n100PCT/100PCT/100PCT.\nADZ YOU HAVE INFO Q.\n--------------------\nZSPD DEP ATIS Q\n0230Z DEP RWY 35R & 34L\nWIND RWY 35R TDZ 040/8MPS MID 040/8MPS\nEND 040/8MPS\nRWY 34L TDZ 040/9MPS MID 050/8MPS END\n050/8MPS\nVIS RWY 35R TDZ 10000M MID 8000M END\n10000M\nVIS RWY 34L TDZ 10000M MID 10000M END\n10000M\nFBL RA\nCLD BKN 330M\nT 12 /DP 10\nQNH 1021 HPA\nCAUTION THE BIRDS NEAR THE RUNWAY\nRWY 35R/35L/34R/34L RWYCC 5/5/5 ISSUED\nAT 0138 WET/WET/WET DPT NR/NR/NR COV\n100PCT/100PCT/100PCT.\nADZ YOU HAVE INFO Q.\n--------------------\n",
  "ZUTF": "✈️ ZUTF ATIS MONITOR\nUpdate: 2026-04-29 10:36:08\n==============================\n\nZUTF ARR ATIS K\n0200Z EXP ILSDME APCH\nLDG RWY 01 & 02\nTA 3000 /TRL 3600\nWIND RWY 01 TDZ 150/1MPS MID 100/2MPS\nEND 100/3MPS\nRWY 02 TDZ 130/1MPS MID 160/1MPS END\n130/2MPS\nCAVOK\nT 19 /DP 11\nQNH 1022 HPA\nDELIVERY FREQUENCY 121.825\nADZ YOU HAVE INFO K.\n--------------------\nZUTF DEP ATIS Z\n2200Z DEP RWY 01\nTA 3000 /TRL 3600\nWIND RWY 01 TDZ 320/2MPS MID 300/1MPS\nEND 300/1MPS\nVIS RWY 01 TDZ 4100M MID 5000M END 5000M\nRVR RWY 01 TDZ P2000M MID P2000M END\nP2000M\nPRFG\nNSC\nT 10 /DP 10\nQNH 1020 HPA\nDELIVERY FREQUENCY 118.8\nADZ YOU HAVE INFO Z.\n--------------------\n",
  "ZGGG": "✈️ ZGGG ATIS MONITOR\nUpdate: 2026-04-29 10:36:06\n==============================\n\nZGGG ARR ATIS T\n0130Z EXP ILS OR VIS APCH\nINDEPENDENT PARL INSTR APCH\nLDG RWY 01L & 02R & 03\nWIND 220 DEG 2 MPS\nVIS 9999\n-SHRA\nCLD SCT 480M /BKN 990M\nT 26 /DP 24\nQNH 1011 HPA\nRNAV IS AVAIL\nADZ YOU HAVE INFO T.\n--------------------\nZGGG DEP ATIS W\n0231Z DEP RWY 01R & 02L & 03\nWIND 320 DEG 7 MPS\nVIS 6000\nSHRA\nCLD SCT 480M /FEW CB 600M /BKN\n990M\nT 24 /DP 21\nQNH 1011 HPA\nDELIVERY FREQ 121.95\nALL RWY RWYCC 5/5/5 ISSUED AT\n0200 ALL PARTS WET NR 100PCT\nRNAV IS AVAIL\nADZ YOU HAVE INFO W.\n--------------------\n",
  "ZGSZ": "✈️ ZGSZ ATIS MONITOR\nUpdate: 2026-04-29 10:36:00\n==============================\n\nZGSZ ARR ATIS I\n0230Z EXP ILS APCH 15\nEXP ILS OR VIS APCH 16R\nWIND 210/2MPS VRB BTN 170/ AND 240/\nVIS 9999M\n-SHRA\nCLD SCT 600M /FEW CB 900M /SCT 1500M\nT 27 /DP 23\nQNH 1011 HPA\nINDEPENDENT PARALLEL DEPARTURES\nDEPENDENT PARALLEL APPROACHES\nEXPECT RNP ILS DME Z APPROACH\nMISSED APPROACH ALTITUDE SETTING\n1200METERS\nWHEN AIRBORNE CONTACT ZHUHAI APPROACH\nADZ YOU HAVE INFO I.\n--------------------\nZGSZ DEP ATIS I\n0230Z DEP RWY 15 & 16L\nWIND 210/2MPS VRB BTN 170/ AND 240/\nVIS 9999M\n-SHRA\nCLD SCT 600M /FEW CB 900M /SCT 1500M\nT 27 /DP 23\nQNH 1011 HPA\nINDEPENDENT PARALLEL DEPARTURES\nDEPENDENT PARALLEL APPROACHES\nEXPECT RNP ILS DME Z APPROACH\nMISSED APPROACH ALTITUDE SETTING\n1200METERS\nWHEN AIRBORNE CONTACT ZHUHAI APPROACH\nADZ YOU HAVE INFO I.\n--------------------\n",
  "ZSNB": "✈️ ZSNB ATIS MONITOR\nUpdate: 2026-04-29 10:35:58\n==============================\n\nZSNB ARR ATIS G\n0100Z EXP ILSDME Z APCH\nLDG RWY 31\nWIND 030 DEG 4 MPS\n350V080 DEG\nVIS 6000\nRA\nCLD SCT 120M /BKN 480M\nT 12 /DP 10\nQNH 1020 HPA\nRWY31 RWYCC 5/5/5 ISSUED\nAT 2000UTC,ALL PARTS WET\nNR 100PCT\nADZ YOU HAVE INFO G.\n--------------------\nZSNB DEP ATIS I\n0400Z DEP RWY 13\nWIND 160 DEG 3 MPS\n110V200 DEG\nCAVOK\nT 30 /DP 14\nQNH 1011 HPA\nADZ YOU HAVE INFO I.\n--------------------\n",
  "RCTP": "✈️ RCTP ATIS MONITOR\nUpdate: 2026-04-29 10:35:57\n==============================\n\nRCTP ARR ATIS B\n0230Z\nEXP ILS APCH\nRWY05L AND RWY05R ARR/DEP. RWY05L CLSD\nBTN 0300Z AND 0330Z FOR INSPECTION.\nWIND 300/05KT VARYING BTN 260 AND 350\nVIS  10 KM OR MORE\nCLD\nFEW  1500FT\nSCT  5000FT\nBKN  20000FT\nT 29 DP 23 QNH 1011HPA\nNOSIG\nCTN BIRD ACTIVITY IN THE VCY OF THE AD.\nINFORM TAIPEI APCH OR TAIPEI TOWER ON\nINITIAL CONTACT\nYOU HAVE INFORMATION B\n--------------------\nRCTP DEP ATIS Z\n0200Z\nEXP ILS APCH\nRWY05L AND RWY05R\nARR/DEP.\nWIND 320/06KT VARYING\nBTN 280 AND 350\nVIS  10 KM OR MORE\nCLD\nFEW  1500FT\nSCT  5000FT\nBKN  20000FT\nT 29 DP 23 QNH 1011HPA\nNOSIG\nCTN BIRD ACTIVITY IN THE\nVCY OF THE AD.\nINFORM TAIPEI APCH OR\nTAIPEI TOWER ON INITIAL\nCONTACT\nYOU HAVE INFORMATION Z\n--------------------\n",
  "RJAA": "✈️ RJAA ATIS MONITOR\nUpdate: 2026-04-29 10:36:01\n==============================\n\nRJAA ARR ATIS N\n0235Z M0230\n(APCH)ILS Y RWY16L\nLDG RWY 16L\nDEP RWY 16R\nDEP FREQ 124.2.\nTWY A1 CLSD.\nM\n290230Z 06010KT 020V080 25KM\nSCT020CU\nBKN035SC 19/13 Q1011/A2988=\nQ/TWO NINE EIGHT EIGHT\nSTP\n--------------------\nRJAA DEP ATIS M\n0224Z M0200\n(APCH)ILS Y RWY16L\nLDG RWY 16L\nDEP RWY 16R\nDEP FREQ 124.2.\nTWY A1 CLSD.\nM\n290200Z 07010KT 25KM FEW020CU\nBKN035SC\nBKN130AC 19/13 Q1011/A2988=\nQ/TWO NINE EIGHT EIGHT\nSTP\n--------------------\n"
}